telert/__init__.py
telert/api.py
telert/cli.py
telert/messaging.py
telert/data/notification-icon.png
telert/data/notification.mp3
telert/monitoring/__init__.py
telert/monitoring/activity_logs.py
telert/monitoring/base.py
telert/monitoring/cli.py
telert/monitoring/cli_logs.py
telert/monitoring/debug_logs.py
telert/monitoring/log.py
telert/monitoring/network.py
telert/monitoring/process.py
telert-0.2.7.dist-info/licenses/LICENSE
telert-0.2.7.dist-info/METADATA
telert-0.2.7.dist-info/WHEEL
telert-0.2.7.dist-info/entry_points.txt
telert-0.2.7.dist-info/top_level.txt
telert-0.2.7.dist-info/RECORD
