Metadata-Version: 2.4
Name: telert
Version: 0.2.7
Summary: Ultimate command monitoring & notification system: Telegram, Slack, Discord, Teams, Pushover, Email, desktop & more. Monitor Python code and CLI tasks with context managers, decorators, and webhooks.
Author-email: Mihir Khandekar <mihirkhandekar@gmail.com>
License-Expression: MIT
Project-URL: Homepage, https://github.com/navig-me/telert
Project-URL: Repository, https://github.com/navig-me/telert
Project-URL: Documentation, https://github.com/navig-me/telert#readme
Project-URL: Bug Tracker, https://github.com/navig-me/telert/issues
Project-URL: VS Code Extension, https://marketplace.visualstudio.com/items?itemName=Navig.telert-vscode
Keywords: telegram,notification,cli,terminal,email,alert,pushover,slack,discord,microsoft-teams,desktop-notifications,monitoring,python-decorators,context-managers,process-monitoring,log-file-monitoring,network-monitoring
Classifier: Development Status :: 4 - Beta
Classifier: Environment :: Console
Classifier: Intended Audience :: Developers
Classifier: Intended Audience :: System Administrators
Classifier: Intended Audience :: Science/Research
Classifier: Operating System :: OS Independent
Classifier: Programming Language :: Python :: 3
Classifier: Programming Language :: Python :: 3.8
Classifier: Programming Language :: Python :: 3.9
Classifier: Programming Language :: Python :: 3.10
Classifier: Programming Language :: Python :: 3.11
Classifier: Programming Language :: Python :: 3.12
Classifier: Topic :: Communications
Classifier: Topic :: Software Development
Classifier: Topic :: System :: Monitoring
Classifier: Topic :: Utilities
Requires-Python: >=3.8
License-File: LICENSE
Requires-Dist: requests>=2.25
Requires-Dist: beautifulsoup4>=4.9.0
Requires-Dist: psutil>=5.9.0
Requires-Dist: ping3>=4.0.0
Provides-Extra: dev
Requires-Dist: build; extra == "dev"
Requires-Dist: twine; extra == "dev"
Requires-Dist: pytest; extra == "dev"
Provides-Extra: audio
Requires-Dist: playsound; extra == "audio"
Provides-Extra: desktop
Provides-Extra: all
Requires-Dist: playsound; extra == "all"
Requires-Dist: psutil; extra == "all"
Requires-Dist: ping3; extra == "all"
Dynamic: license-file
